pandas_xlsx_tables/__init__.py
pandas_xlsx_tables/from_xlsx_tables.py
pandas_xlsx_tables/to_xlsx_table.py
pandas_xlsx_tables/utils.py
pandas_xlsx_tables-1.0.0.dist-info/AUTHORS.md
pandas_xlsx_tables-1.0.0.dist-info/LICENSE.txt
pandas_xlsx_tables-1.0.0.dist-info/METADATA
pandas_xlsx_tables-1.0.0.dist-info/WHEEL
pandas_xlsx_tables-1.0.0.dist-info/top_level.txt
pandas_xlsx_tables-1.0.0.dist-info/RECORD
