Metadata-Version: 2.1
Name: pandas-xlsx-tables
Version: 1.0.0
Summary: Read and write excel tables with pandas
Home-page: https://github.com/VanOord/pandas-xlsx-tables
Author: Thijs Damsma
Author-email: tdamsma@gmail.com
License: MIT
Project-URL: Documentation, https://pandas-xlsx-tables.readthedocs.io/en/latest/
Project-URL: Source, https://github.com/VanOord/pandas-xlsx-tables
Project-URL: Changelog, https://github.com/VanOord/pandas-xlsx-tables/blob/master/CHANGELOG.md
Project-URL: Tracker, https://github.com/VanOord/pandas-xlsx-tables/issues
Platform: any
Classifier: Development Status :: 4 - Beta
Classifier: Programming Language :: Python
Requires-Python: >=3.8
License-File: LICENSE.txt
License-File: AUTHORS.md
Requires-Dist: pandas
Requires-Dist: openpyxl (>=3)
Requires-Dist: xlsxwriter
Provides-Extra: dev
Requires-Dist: black ; extra == 'dev'
Requires-Dist: flake8 ; extra == 'dev'
Requires-Dist: flake8-isort ; extra == 'dev'
Requires-Dist: mypy ; extra == 'dev'
Requires-Dist: pre-commit ; extra == 'dev'
Provides-Extra: testing
Requires-Dist: openpyxl-stubs ; extra == 'testing'
Requires-Dist: pandas-stubs ; extra == 'testing'
Requires-Dist: pytest ; extra == 'testing'
Requires-Dist: pytest-black ; extra == 'testing'
Requires-Dist: pytest-cov ; extra == 'testing'
Requires-Dist: pytest-isort ; extra == 'testing'
Requires-Dist: pytest-mypy ; extra == 'testing'
Requires-Dist: pytest-sugar ; extra == 'testing'
Requires-Dist: tox ; extra == 'testing'
